squall_router-0.2.1.dist-info/METADATA
squall_router-0.2.1.dist-info/WHEEL
squall_router/__init__.py
squall_router/__init__.pyi
squall_router/py.typed
squall_router/squall_router.cpython-310-x86_64-linux-gnu.so
squall_router-0.2.1.dist-info/RECORD
